<?xml version="1.0" encoding="UTF-8" ?>
<!DOCTYPE devices PUBLIC "-//YARP//DTD robotInterface 1.0//EN" "http://www.icub.org/DTD/robotInterfaceV1.0.dtd">
<devices robot="iCubDaejeon01" build="0">
    <device name="left_arm_VFTserver" type="virtualAnalogServer">
        <param name="period">       10                  </param>
        <param name="deviceId">     left_arm                </param>
        
        <paramlist name="networks">
            <elem name="net_VFT_LA">  0  5  0  5 </elem> 
        </paramlist>

        <param name="name">          /left_arm                </param>

        <action phase="startup" level="5" type="attach">
            <paramlist name="networks">
            <elem name="net_VFT_LA">  left_arm_virtual_strain </elem>    
            </paramlist>
        </action>

        <action phase="shutdown" level="5" type="detach" />
    </device>
</devices>


